eems/ds18b20.py
eems/exports.py
eems/scripts.py
eems/test.py
eems/__init__.py
eems/data/help.txt
eems-0.1.0.4b1.dist-info/DESCRIPTION.rst
eems-0.1.0.4b1.dist-info/entry_points.txt
eems-0.1.0.4b1.dist-info/METADATA
eems-0.1.0.4b1.dist-info/metadata.json
eems-0.1.0.4b1.dist-info/RECORD
eems-0.1.0.4b1.dist-info/top_level.txt
eems-0.1.0.4b1.dist-info/WHEEL
