Metadata-Version: 2.0
Name: eems
Version: 0.1.0.4b1
Summary: eems - easy energy monitoring system
Home-page: https://github.com/enricoba/eems
Author: Henrik Baran, Aurofree Hoehn
Author-email: henrik.baran@online.de, a.hoehn@mailbox.org
License: MIT
Keywords: easy energy monitoring system raspberrry pi
Platform: 
Classifier: Development Status :: 4 - Beta
Classifier: Intended Audience :: End Users/Desktop
Classifier: Intended Audience :: Education
Classifier: Intended Audience :: Manufacturing
Classifier: Topic :: Scientific/Engineering
Classifier: License :: OSI Approved :: MIT License
Classifier: Programming Language :: Python :: 2.7
